[
  {
    "data": {
      "skillname": "JavaScript",
      "level": "advanced",
      "imageLogo": "jsLogo",
      "onClickUrl": "https://developer.mozilla.org/en-US/docs/Web/JavaScript"
    }
  },
  {
    "data": {
      "skillname": "TypeScript",
      "level": "advanced",
      "imageLogo": "tsLogo",
      "onClickUrl": "https://www.typescriptlang.org"
    }
  },
  {
    "data": {
      "skillname": "HTML",
      "level": "advanced",
      "imageLogo": "htmlLogo",
      "onClickUrl": "https://developer.mozilla.org/en-US/docs/Web/HTML"
    }
  },
  {
    "data": {
      "skillname": "CSS",
      "level": "medium",
      "imageLogo": "cssLogo",
      "onClickUrl": "https://developer.mozilla.org/en-US/docs/Web/CSS"
    }
  },
  {
    "data": {
      "skillname": "Node.JS",
      "level": "advanced",
      "imageLogo": "nodeLogo",
      "onClickUrl": "https://nodejs.org/en/docs"
    }
  },
  {
    "data": {
      "skillname": "Express.JS",
      "level": "medium",
      "imageLogo": "expressLogo",
      "onClickUrl": "https://expressjs.com/es"
    }
  },
  {
    "data": {
      "skillname": "React.JS",
      "level": "medium",
      "imageLogo": "reactLogo",
      "onClickUrl": "https://react.dev"
    }
  },
  {
    "data": {
      "skillname": "Next.JS",
      "level": "begginer",
      "imageLogo": "nextLogo",
      "onClickUrl": "https://nextjs.org/"
    }
  },
  {
    "data": {
      "skillname": "MongoDB",
      "level": "begginer",
      "imageLogo": "mongoLogo",
      "onClickUrl": "https://www.mongodb.com/"
    }
  },
  {
    "data": {
      "skillname": "C-Sharp",
      "level": "begginer",
      "imageLogo": "csharpLogo",
      "onClickUrl": "https://learn.microsoft.com/en-us/dotnet/csharp/"
    }
  },
  {
    "data": {
      "skillname": "Python",
      "level": "advanced",
      "imageLogo": "pyLogo",
      "onClickUrl": "https://www.python.org"
    }
  },
  {
    "data": {
      "skillname": "Git",
      "level": "medium",
      "imageLogo": "gitLogo",
      "onClickUrl": "https://git-scm.com/doc"
    }
  },
  {
    "data": {
      "skillname": "C (1972)",
      "level": "begginer",
      "imageLogo": "cLogo",
      "onClickUrl": "https://es.wikipedia.org/wiki/C_(lenguaje_de_programaci%C3%B3n)"
    }
  },
  {
    "data": {
      "skillname": "VSCode",
      "level": "advanced",
      "imageLogo": "vscLogo",
      "onClickUrl": "https://code.visualstudio.com/"
    }
  }
]
